FM14_transform/__init__.py
FM14_transform/bufr2geojson.py
FM14_transform/data2bufr.py
FM14_transform/elastic.py
FM14_transform/opensearch.py
FM14_transform/provider.py
FM14_transform/resources/307090_template.json
FM14_transform/resources/__init__.py
FM14_transform-0.0.47.dist-info/METADATA
FM14_transform-0.0.47.dist-info/WHEEL
FM14_transform-0.0.47.dist-info/entry_points.txt
FM14_transform-0.0.47.dist-info/top_level.txt
FM14_transform-0.0.47.dist-info/RECORD
