Metadata-Version: 2.1
Name: FM14_transform
Version: 0.0.47
Summary: Package for converting FM14 SYNOP MOBIL TAC messages or an individual METAR message to BUFR4
Author-email: Alexander Thompson <alexander.thompson@noaa.gov>
Project-URL: Homepage, https://github.com/pypa/sampleproject
Project-URL: Bug Tracker, https://github.com/pypa/sampleproject/issues
Keywords: WMO,SYNOP MOBIL,FM-14,BUFR,decoding,weather,observations
Classifier: Development Status :: 1 - Planning
Requires-Python: >=3.7
Requires-Dist: csv2bufr
Requires-Dist: eccodes
Requires-Dist: cfunits
Requires-Dist: pymetdecoder
Requires-Dist: opensearch-py
